setup.py
aognet/__init__.py
aognet/aognet.py
aognet/aognet_search.py
aognet/config.py
aognet/generate_aognet.py
aognet/operator.py
aognet.egg-info/PKG-INFO
aognet.egg-info/SOURCES.txt
aognet.egg-info/dependency_links.txt
aognet.egg-info/top_level.txt
aognet/aog/AOG.py
aognet/aog/AOG_Test.py
aognet/aog/AOG_Util.py
aognet/aog/AOG_Viz.py
aognet/aog/AOG_bk.py
aognet/aog/__init__.py